rshub/__init__.py
rshub/check_authenticity.py
rshub/load_files.py
rshub/output_manager.py
rshub/submit_jobs.py
rshub-0.3.5.dist-info/licenses/LICENSE
rshub-0.3.5.dist-info/METADATA
rshub-0.3.5.dist-info/WHEEL
rshub-0.3.5.dist-info/top_level.txt
rshub-0.3.5.dist-info/RECORD
