Metadata-Version: 2.4
Name: rshub
Version: 0.3.5
Summary: This a python package to run and download submitted files on RSHub
Author-email: Yiwen Fang <yiwenfang@intl.zju.edu.cn>
License: MIT
Project-URL: Homepage, https://rshub.zju.edu.cn
Project-URL: demos, https://github.com/zjuiEMLab/rshub/tree/main/demo
Keywords: toolbox,utilities
Requires-Python: >=3.8
License-File: LICENSE
Requires-Dist: requests
Requires-Dist: scipy
Requires-Dist: tqdm
Requires-Dist: h5py
Requires-Dist: pandas
Dynamic: license-file
